davidzhang_oceanbase_mcp-0.0.1.dist-info/licenses/LICENSE
oceanbase_mcp/__init__.py
oceanbase_mcp/__main__.py
oceanbase_mcp/server.py
davidzhang_oceanbase_mcp-0.0.1.dist-info/METADATA
davidzhang_oceanbase_mcp-0.0.1.dist-info/WHEEL
davidzhang_oceanbase_mcp-0.0.1.dist-info/entry_points.txt
davidzhang_oceanbase_mcp-0.0.1.dist-info/top_level.txt
davidzhang_oceanbase_mcp-0.0.1.dist-info/RECORD
