Metadata-Version: 2.4
Name: davidzhang-oceanbase-mcp
Version: 0.0.1
Summary: A Model Context Protocol (MCP) server that enables secure interaction with OceanBase databases. This server allows AI assistants to list tables, read data, and execute SQL queries through a controlled interface, making database exploration and analysis safer and more structured.
License:                                  Apache License
Keywords: oceanbase,mcp
Classifier: Development Status :: 3 - Alpha
Classifier: Programming Language :: Python :: 3
Classifier: Programming Language :: Python :: 3.11
Requires-Python: >=3.11
License-File: LICENSE
Requires-Dist: mcp[cli]>=1.0.0
Requires-Dist: fastmcp>=2.5.1
Requires-Dist: mysql-connector-python>=9.1.0
Requires-Dist: python-dotenv
Requires-Dist: beautifulsoup4>=4.13.3
Requires-Dist: certifi>=2025.4.26
Requires-Dist: requests
Dynamic: license-file
